{
  "project_info": {
    "project_number": "987734592271",
    "project_id": "kerasaan-estore",
    "storage_bucket": "kerasaan-estore.appspot.com"
  },
  "client": [
    {
      "client_info": {
        "mobilesdk_app_id": "1:987734592271:android:f1b7db1d183d68785e8c7a",
        "android_client_info": {
          "package_name": "com.kstore.kerasaanestore"
        }
      },
      "oauth_client": [
        {
          "client_id": "987734592271-67ilmsn82862tjvqebhk33n4fk3m743d.apps.googleusercontent.com",
          "client_type": 3
        }
      ],
      "api_key": [
        {
          "current_key": "AIzaSyDfwwOmCkWhjJhr_GtPHlbXAFUWyCAgVPQ"
        }
      ],
      "services": {
        "appinvite_service": {
          "other_platform_oauth_client": [
            {
              "client_id": "987734592271-67ilmsn82862tjvqebhk33n4fk3m743d.apps.googleusercontent.com",
              "client_type": 3
            }
          ]
        }
      }
    }
  ],
  "configuration_version": "1"
}